{
    "permissions": {
        "auth": {
            "amplifyteame7d43ec3": [
                "create",
                "read",
                "update",
                "delete"
            ]
        },
        "storage": {
            "s3": [
                "create",
                "read",
                "update",
                "delete"
            ]
        },
        "api": {
            "amplifyteam": [
                "create",
                "read",
                "update",
                "delete"
            ]
        }
    }
}